[
    {
        "key": "dbln",
        "value": "%7B%2261583897035803%22%3A%22pcViTe07%22%2C%2261583543857836%22%3A%22szPVLS6v%22%7D",
        "domain": "facebook.com",
        "path": "/login/device-based/",
        "hostOnly": false,
        "creation": "2025-11-18T06:38:55.481Z",
        "lastAccessed": "2025-11-18T06:38:55.481Z"
    },
    {
        "key": "datr",
        "value": "nngWaWEBZY5yLUuHt8GM7vdD",
        "domain": "facebook.com",
        "path": "/",
        "hostOnly": false,
        "creation": "2025-11-18T06:38:55.481Z",
        "lastAccessed": "2025-11-18T06:38:55.481Z"
    },
    {
        "key": "sb",
        "value": "nngWaSy5LhbjoLoBscOlTF4G",
        "domain": "facebook.com",
        "path": "/",
        "hostOnly": false,
        "creation": "2025-11-18T06:38:55.481Z",
        "lastAccessed": "2025-11-18T06:38:55.481Z"
    },
    {
        "key": "ps_l",
        "value": "1",
        "domain": "facebook.com",
        "path": "/",
        "hostOnly": false,
        "creation": "2025-11-18T06:38:55.481Z",
        "lastAccessed": "2025-11-18T06:38:55.481Z"
    },
    {
        "key": "ps_n",
        "value": "1",
        "domain": "facebook.com",
        "path": "/",
        "hostOnly": false,
        "creation": "2025-11-18T06:38:55.481Z",
        "lastAccessed": "2025-11-18T06:38:55.481Z"
    },
    {
        "key": "locale",
        "value": "en_US",
        "domain": "facebook.com",
        "path": "/",
        "hostOnly": false,
        "creation": "2025-11-18T06:38:55.481Z",
        "lastAccessed": "2025-11-18T06:38:55.481Z"
    },
    {
        "key": "vpd",
        "value": "v1%3B735x393x2.75",
        "domain": "facebook.com",
        "path": "/",
        "hostOnly": false,
        "creation": "2025-11-18T06:38:55.481Z",
        "lastAccessed": "2025-11-18T06:38:55.481Z"
    },
    {
        "key": "pas",
        "value": "61583897035803%3AmZe8O0dA3Z%2C61583543857836%3AYItHjpTUip",
        "domain": "facebook.com",
        "path": "/",
        "hostOnly": false,
        "creation": "2025-11-18T06:38:55.481Z",
        "lastAccessed": "2025-11-18T06:38:55.481Z"
    },
    {
        "key": "m_pixel_ratio",
        "value": "2.75",
        "domain": "facebook.com",
        "path": "/",
        "hostOnly": false,
        "creation": "2025-11-18T06:38:55.481Z",
        "lastAccessed": "2025-11-18T06:38:55.481Z"
    },
    {
        "key": "wd",
        "value": "393x869",
        "domain": "facebook.com",
        "path": "/",
        "hostOnly": false,
        "creation": "2025-11-18T06:38:55.481Z",
        "lastAccessed": "2025-11-18T06:38:55.481Z"
    },
    {
        "key": "c_user",
        "value": "61583543857836",
        "domain": "facebook.com",
        "path": "/",
        "hostOnly": false,
        "creation": "2025-11-18T06:38:55.481Z",
        "lastAccessed": "2025-11-18T06:38:55.481Z"
    },
    {
        "key": "xs",
        "value": "13%3A3OQXtTW1AUx8VQ%3A2%3A1763435795%3A-1%3A-1",
        "domain": "facebook.com",
        "path": "/",
        "hostOnly": false,
        "creation": "2025-11-18T06:38:55.481Z",
        "lastAccessed": "2025-11-18T06:38:55.481Z"
    },
    {
        "key": "fr",
        "value": "0xlhQrhWTrj1ZBxa9.AWdlKc7l4VOMjikDf6mZNS86rk1eBpIJ9oFxZcQqjoNWgsPxSUM.BpFnie..AAA.0.0.BpG-UV.AWc8R3aIKeNPWbzkMUhrBQWW0SU",
        "domain": "facebook.com",
        "path": "/",
        "hostOnly": false,
        "creation": "2025-11-18T06:38:55.481Z",
        "lastAccessed": "2025-11-18T06:38:55.481Z"
    },
    {
        "key": "fbl_st",
        "value": "101425327%3BT%3A29390596",
        "domain": "facebook.com",
        "path": "/",
        "hostOnly": false,
        "creation": "2025-11-18T06:38:55.481Z",
        "lastAccessed": "2025-11-18T06:38:55.481Z"
    },
    {
        "key": "wl_cbv",
        "value": "v2%3Bclient_version%3A2987%3Btimestamp%3A1763435797",
        "domain": "facebook.com",
        "path": "/",
        "hostOnly": false,
        "creation": "2025-11-18T06:38:55.481Z",
        "lastAccessed": "2025-11-18T06:38:55.481Z"
    }
]
